{
  "AbbyMod:Dabigail": {
    "NAME": "아비게일",
    "DESCRIPTION": "소멸. NL [E] [E] [E] [E] 를 얻습니다.",
    "UPGRADE_DESCRIPTION": "소멸. NL [E] [E] [E] [E] [E] [E] 를 얻습니다."
  },
  "AbbyMod:Abby_NP": {
    "NAME": "클리포트 리좀",
    "DESCRIPTION": "제거. NL 피해를 !D! 줍니다. NL abbymod:열쇠구멍 을 얻습니다."
  },
  "AbbyMod:Ab_Defend": {
    "NAME": "방어",
    "DESCRIPTION": "방어도 를 !B! 만큼 X 회 얻습니다. NL 최대 3 회까지 가능합니다."
  },
  "AbbyMod:Ab_Strike": {
    "NAME": "광기의 타격",
    "DESCRIPTION": "피해를 !D! 줍니다. NL abbymod:광기 를 1 얻습니다."
  },
  "AbbyMod:AdultWords": {
    "NAME": "어른의 언어",
    "DESCRIPTION": "피해를 !D! 줍니다. NL 방어도 를 무시합니다."
  },
  "AbbyMod:ChocoKey": {
    "NAME": "초코 열쇠",
    "DESCRIPTION": "abbymod:열쇠. NL 방어도 를 !B! 얻습니다. NL 피해를 !D! 줍니다."
  },
  "AbbyMod:ConsumeFlesh": {
    "NAME": "살점 섭취",
    "DESCRIPTION": "전투에서 승리 시 최대 체력이 !M! 증가합니다."
  },
  "AbbyMod:DemonPancake": {
    "NAME": "악마의 팬케이크",
    "DESCRIPTION": "힘 을 2 얻고 민첩 을 !M! 얻습니다."
  },
  "AbbyMod:EyesOfMadness": {
    "NAME": "광기의 눈",
    "DESCRIPTION": "소멸. NL [E] [E] 를 얻습니다.",
    "UPGRADE_DESCRIPTION": "보존. NL 소멸. NL [E] [E] 를 얻습니다."
  },
  "AbbyMod:FamiliarShield": {
    "NAME": "친숙한 방패",
    "DESCRIPTION": "소멸. NL  방어도 를 !B! 얻습니다. NL 판금 갑옷 이 !M! 보다 낮다면, 판금 갑옷 을 !M! 으로 만듭니다."
  },
  "AbbyMod:FleetingSanity": {
    "NAME": "덧없는 정신",
    "DESCRIPTION": "소멸. NL abbymod:광기 를 5 얻습니다.",
    "UPGRADE_DESCRIPTION": "abbymod:광기 를 5 얻습니다.."
  },
  "AbbyMod:ForeheadBeam": {
    "NAME": "이마 빔",
    "DESCRIPTION": "적 전체에게 피해를 !D! 주고 취약 을 !M! 부여합니다. NL abbymod:광기 를 3 얻습니다."
  },
  "AbbyMod:Keyblade": {
    "NAME": "열쇠칼",
    "DESCRIPTION": "피해를 !D! 줍니다. NL 이번 턴에만 적의 힘 을 !M! 감소시킵니다."
  },
  "AbbyMod:LargeTentacle": {
    "NAME": "거대한 촉수",
    "DESCRIPTION": "피해를 !D! 줍니다."
  },
  "AbbyMod:LossOfSanity": {
    "NAME": "정신 상실",
    "DESCRIPTION": "abbymod:광기 2 를 X 번 얻습니다.",
    "UPGRADE_DESCRIPTION": "abbymod:광기 2 를 X+2 번 얻습니다.."
  },
  "AbbyMod:OldOneLimb": {
    "NAME": "옛 존재의 수족",
    "DESCRIPTION": "소멸. NL 불가침 을 1 얻습니다. NL 최대 체력을 !M! 잃습니다."
  },
  "AbbyMod:SanityCheck": {
    "NAME": "정신 검사",
    "DESCRIPTION": "소멸. NL 버린 카드 더미에서 카드를 골라 뽑을 카드 더미 맨 위에 놓습니다. 이번 전투 동안 비용이 2 감소합니다."
  },
  "AbbyMod:SavingThrow": {
    "NAME": "구원의 던지기",
    "DESCRIPTION": "소멸. NL 방어도 를 !B! 얻습니다."
  },
  "AbbyMod:TeddyBear": {
    "NAME": "테디베어",
    "DESCRIPTION": "소멸. NL 현재 가지고 있는 abbymod:광기 를 모두 잃고 체력을 10 회복합니다.",
    "UPGRADE_DESCRIPTION": "선천성. NL 소멸. NL 현재 가지고 있는 abbymod:광기 를 모두 잃고 체력을 10 회복합니다."
  },
  "AbbyMod:TentacleSwarm": {
    "NAME": "촉수 무리",
    "DESCRIPTION": "피해를 !D! 만큼 !M! 번 줍니다."
  },
  "AbbyMod:WitchTrial": {
    "NAME": "마녀 재판",
    "DESCRIPTION": "피해를 !D! 줍니다. NL 약화 를 !M! 부여합니다."
  },
  "AbbyMod:ImpossibleGeometry": {
    "NAME": "불가능한 기하학",
    "DESCRIPTION": "가시 를 !M! 얻습니다."
  },
  "AbbyMod:PapaProtection": {
    "NAME": "파파의 보호",
    "DESCRIPTION": "방어도 를 !B! 얻습니다. NL abbymod:광기 를 !M! 얻습니다."
  },
  "AbbyMod:Thflth": {
    "NAME": "Thflthkh'ngha",
    "DESCRIPTION": "방어도 를 !B! 얻습니다. NL 힘 을 3 얻습니다. NL abbymod:광기 를 3 얻습니다. NL abbymod:열쇠구멍 을 잃습니다."
  },
  "AbbyMod:Ygna": {
    "NAME": "Ygnaiih",
    "DESCRIPTION": "방어도 를 !B! 얻습니다. NL 민첩 을 2 얻습니다.  NL abbymod:광기 를 3 얻습니다. NL abbymod:열쇠구멍 을 잃습니다."
  },
  "AbbyMod:PrayerOfFaith": {
    "NAME": "신념의 기도",
    "DESCRIPTION": "매 턴이 시작할 때마다 힘 을 2 얻고 민첩 을 1 얻습니다."
  },
  "AbbyMod:Takeuchi": {
    "NAME": "타케우치",
    "DESCRIPTION": "소멸. NL 피해를 !D! 줍니다. NL 카드를 뽑고, 2 장 복사하여 가져옵니다."
  },
  "AbbyMod:Kinoko": {
    "NAME": "버섯",
    "DESCRIPTION": "피해를 !D! 줍니다. NL 내 손의 카드를 모두 버리고, 카드를 !M! 장 뽑습니다."
  },
  "AbbyMod:Kuroboshi": {
    "NAME": "검은 별",
    "DESCRIPTION": "방어도 를 !B! 만큼 !M! 번 얻습니다."
  },
  "AbbyMod:Hitomi": {
    "NAME": "눈동자",
    "DESCRIPTION": "판금 갑옷 을 !M! 얻습니다."
  },
  "AbbyMod:Meteo": {
    "NAME": "메테오",
    "DESCRIPTION": "이번 턴에 내 손에 있는 카드를 보존 합니다. NL 이번 전투 동안 이 카드의 비용이 1 증가합니다."
  },
  "AbbyMod:CommandSpell": {
    "NAME": "주문 외우기",
    "DESCRIPTION": "abbymod:덧없음. NL 임시 체력을 !M! 얻습니다."
  },
  "AbbyMod:FlyingMascot": {
    "NAME": "날으는 마스코트",
    "DESCRIPTION": "내 재생 을 제거하고 NL !M! 의 재생 을 얻습니다."
  },
  "AbbyMod:SweetPancakes": {
    "NAME": "달콤한 팬케이크!",
    "DESCRIPTION": "abbymod:덧없음. NL 최대 체력이 !M! 증가합니다."
  },
  "AbbyMod:RecklessSlam": {
    "NAME": "무모한 돌진",
    "DESCRIPTION": "피해를 !D! 주고, 약화 를 !M! 받습니다."
  },
  "AbbyMod:BadGirl": {
    "NAME": "나쁜 아이",
    "DESCRIPTION": "피해를 !D! 줍니다. NL 적의 힘을 !M! 만큼 감소시키고, 내 민첩 을 1 잃습니다."
  },
  "AbbyMod:SilverKey": {
    "NAME": "은 열쇠",
    "DESCRIPTION": "abbymod:열쇠. NL 방어도 를 !B! 얻습니다. NL 피해를 !D! 줍니다."
  },
  "AbbyMod:ExposeNavel": {
    "NAME": "배꼽 노출",
    "DESCRIPTION": "피해를 !D! 줍니다. NL 약화 를 !M! 부여합니다. NL 이번 턴에만 적의 힘 을 !M! 감소시킵니다.",
    "UPGRADE_DESCRIPTION": "진액 파워"
  },
  "AbbyMod:LiftSkirt": {
    "NAME": "치마 들추기",
    "DESCRIPTION": "피해를 !D! 줍니다. NL 약화 를 !M! 부여합니다. NL 소멸된 카드를 1장 선택해 가져옵니다.",
    "UPGRADE_DESCRIPTION": "4차원 주머니"
  },
  "AbbyMod:InsaneStrike": {
    "NAME": "광란의 타격",
    "DESCRIPTION": "피해를 !D! 만큼 두번 줍니다. NL 손상 을 2 얻고 약화 를 1 얻습니다."
  },
  "AbbyMod:AlignStars": {
    "NAME": "별 정렬",
    "DESCRIPTION": "!M! 턴간 카운트다운 하고, 매 턴마다 에너지가 0 일 때만 5의 힘 과 2의 민첩 을 얻습니다."
  },
  "AbbyMod:BlackKey": {
    "NAME": "검은 열쇠",
    "DESCRIPTION": "abbymod:열쇠. NL 방어도 를 !B! 얻습니다. NL 피해를 !D! 줍니다."
  },
  "AbbyMod:MysteryKey": {
    "NAME": "??? 열쇠",
    "DESCRIPTION": "abbymod:열쇠. NL 방어도 를 !B! 얻습니다. NL 피해를 !D! 줍니다."
  },
  "AbbyMod:SlimyBody": {
    "NAME": "미끈한 몸",
    "DESCRIPTION": "소멸. NL 불가침 을 1 얻습니다. NL 점액투성이 카드를 !M! 만큼 내 손에 추가합니다."
  },
  "AbbyMod:VoidPriest": {
    "NAME": "Hafh'drn",
    "DESCRIPTION": "턴 시작시 방어도 가 사라지지 않습니다. NL 카드를 사용할 때마다 소멸 시킵니다.",
    "UPGRADE_DESCRIPTION": "턴 시작시 방어도 가 사라지지 않습니다. NL 카드를 사용할 때마다 소멸 시킵니다. NL 방어도 를 !B! 얻습니다."
  },
  "AbbyMod:VoidHeretic": {
    "NAME": "Hlirgh",
    "DESCRIPTION": "힘 을 !M! 얻고 abbymod:광기 를 8 얻습니다. NL 취약 과 손상 을 12 얻습니다."
  },
  "AbbyMod:VoidWhispers": {
    "NAME": "속삭임",
    "DESCRIPTION": "매 턴마다 내 에너지 만큼의 abbymod:광기 를 얻습니다."
  },
  "AbbyMod:PantyShot": {
    "NAME": "팬티 샷",
    "DESCRIPTION": "피해를 !D! 줍니다. NL abbymod:광기 를 3 얻습니다.",
    "UPGRADE_DESCRIPTION": "마녀의 타격"
  },
  "AbbyMod:AbsoluteCorruption": {
    "NAME": "완전한 타락",
    "DESCRIPTION": "혼란 상태가 되고 매 턴마다 추가로 카드를 1 장 뽑습니다."
  },
  "AbbyMod:MindCleanse": {
    "NAME": "마음 정화",
    "DESCRIPTION": "방어도 를 !B! 만큼 X 번 얻습니다. NL abbymod:열쇠구멍 을 잃습니다."
  },
  "AbbyMod:PowerGamer": {
    "NAME": "파워 게이머",
    "DESCRIPTION": "내 손에 있는 카드를 모두 버립니다. NL abbymod:광기 를 !M! 얻습니다."
  },
  "AbbyMod:MeltBrain": {
    "NAME": "뇌 용해",
    "DESCRIPTION": "소멸. NL 보존. NL abbymod:열쇠구멍 을 잃고, 잃은 abbymod:열쇠구멍 하나당 [E] 와 2 의 abbymod:광기 를 얻습니다.",
    "UPGRADE_DESCRIPTION": "선천성, 소멸, 보존. NL abbymod:열쇠구멍 을 잃고, 잃은 abbymod:열쇠구멍 하나당 [E] 와 2 의 abbymod:광기 를 얻습니다."
  },
  "AbbyMod:HeroCreationA": {
    "NAME": "영웅 창조 A",
    "DESCRIPTION": "소멸. NL 힘 을 4 얻고, 턴이 끝날 때 힘 을 3 잃습니다."
  },
  "AbbyMod:WorldStrongest": {
    "NAME": "세계 최강",
    "DESCRIPTION": "abbymod:덧없음. NL 힘 을 !M! 얻고 민첩 을 !M! 얻습니다."
  },
  "AbbyMod:HolidayWishes": {
    "NAME": "휴일의 소원",
    "DESCRIPTION": "abbymod:무덤. NL 힘 과 민첩 을 2 얻습니다."
  },
  "AbbyMod:LifeSentence": {
    "NAME": "종신형",
    "DESCRIPTION": "소멸. NL 적 전체에게 피해를 !D! 주고 약화 를 99 부여합니다."
  },
  "AbbyMod:PreciousMemories": {
    "NAME": "소중한 추억들",
    "DESCRIPTION": "abbymod:열쇠구멍 을 !M! 얻습니다."
  },
  "AbbyMod:SuperMuscular": {
    "NAME": "헬갤러",
    "DESCRIPTION": "abbymod:무덤. NL abbymod:광기 를 5 얻습니다. NL 힘 을 1 얻습니다.",
    "UPGRADE_DESCRIPTION": "선천성. NL abbymod:광기 를 5 얻습니다. NL 힘 을 1 얻습니다."
  },
  "AbbyMod:WormHole": {
    "NAME": "웜홀",
    "DESCRIPTION": "매 턴이 끝날 때마다 버린 카드 더미에서 카드를 골라 뽑을 카드 더미 위에 놓습니다."
  },
  "AbbyMod:CosmicSpark": {
    "NAME": "우주의 불꽃",
    "DESCRIPTION": "abbymod:자동, 소멸. NL 매 턴 시작시 클리포스 리좀 카드를 얻습니다. NL 임시 체력 을 3 얻습니다."
  },
  "AbbyMod:Ab_PuppyEyes": {
    "NAME": "Puppy Eyes",
    "DESCRIPTION": "선천성, 보존, 제거. NL 방어도 를 !B! 얻습니다. NL 손상 을 2 얻습니다."
  },
  "AbbyMod:Ab_DarkestPact": {
    "NAME": "암울한 계약",
    "DESCRIPTION": "손상 을 !M! 얻습니다. !M! 턴 후에 민첩 을 5 얻습니다."
  },
  "AbbyMod:Ab_OldOneTrigger": {
    "NAME": "옛 존재의 방아쇠",
    "DESCRIPTION": "판금 갑옷 을 !M! 얻습니다. NL 3 턴 후 모든 판금 갑옷 을 잃습니다."
  },
  "AbbyMod:Ab_SwirlOfMadness": {
    "NAME": "광기의 소용돌이",
    "DESCRIPTION": "적 전체에게 피해를 !D! 줍니다. NL abbymod:열쇠구멍 갯수만큼 반복합니다."
  },
  "AbbyMod:Ab_FiveStars": {
    "NAME": "다섯개의 별",
    "DESCRIPTION": "적 전체에게 피해를 !D! 줍니다. NL 만약 [E] 가 정확히 5 라면 두 번 사용됩니다."
  }
}